kimolib/__init__.py
kimolib-10.0.dist-info/METADATA
kimolib-10.0.dist-info/WHEEL
kimolib-10.0.dist-info/entry_points.txt
kimolib-10.0.dist-info/top_level.txt
kimolib-10.0.dist-info/RECORD
